tkinterweb_tkhtml/__init__.py
tkinterweb_tkhtml/tkhtml/COPYRIGHT
tkinterweb_tkhtml/tkhtml/linux_armv7l/libTkhtml3.0.so
tkinterweb_tkhtml/tkhtml/macosx_10_6_x86_64/libTkhtml3.0.dylib
tkinterweb_tkhtml/tkhtml/macosx_11_0_arm64/libTkhtml3.0.dylib
tkinterweb_tkhtml/tkhtml/manylinux1_i686/libTkhtml3.0.so
tkinterweb_tkhtml/tkhtml/manylinux1_x86_64/libTkhtml3.0.so
tkinterweb_tkhtml/tkhtml/manylinux1_x86_64/libTkhtml3.1.so
tkinterweb_tkhtml/tkhtml/manylinux2014_aarch64/libTkhtml3.0.so
tkinterweb_tkhtml/tkhtml/win32/libTkhtml3.0.dll
tkinterweb_tkhtml/tkhtml/win_amd64/COPYING-CAIRO-LGPL-2.1
tkinterweb_tkhtml/tkhtml/win_amd64/libTkhtml3.0.dll
tkinterweb_tkhtml/tkhtml/win_amd64/libTkhtml3.1.dll
tkinterweb_tkhtml/tkhtml/win_amd64/libcairo-2.dll
tkinterweb_tkhtml-1.1.3.dist-info/LICENSE.md
tkinterweb_tkhtml-1.1.3.dist-info/METADATA
tkinterweb_tkhtml-1.1.3.dist-info/WHEEL
tkinterweb_tkhtml-1.1.3.dist-info/top_level.txt
tkinterweb_tkhtml-1.1.3.dist-info/RECORD
