Metadata-Version: 2.1
Name: tkinterweb-tkhtml
Version: 1.1.3
Summary: HTML/CSS viewer for Tkinter
Home-page: https://github.com/Andereoo/TkinterWeb-Tkhtml
License: MIT
Keywords: tkinter,Tkinter,tkhtml,Tkhtml,Tk,HTML,CSS,webbrowser
Classifier: Intended Audience :: Developers
Classifier: License :: Freeware
Classifier: License :: OSI Approved :: MIT License
Classifier: Natural Language :: English
Classifier: Programming Language :: Python
Classifier: Programming Language :: Python :: 3
Classifier: Topic :: Software Development
Requires-Python: >=3.2
License-File: LICENSE.md
